Dronacharya/Dronacharya.py
Dronacharya/__init__.py
Dronacharya/__main__.py
Dronacharya-1.dist-info/METADATA
Dronacharya-1.dist-info/WHEEL
Dronacharya-1.dist-info/top_level.txt
Dronacharya-1.dist-info/RECORD
