Metadata-Version: 2.1
Name: Dronacharya
Version: 1
Summary: Dronacharya: Ultimate Guru
Author: Suraj Sharma
Author-email: Surajsharma963472@gmail.com
Keywords: Surya,Vaidya,Dronacharya,python tutorial,Suraj,Teacher,groq
Requires-Dist: pathlib
Requires-Dist: colorama
Requires-Dist: edge-tts
Requires-Dist: pygame
Requires-Dist: groq
